passthroughauth/__init__.py
passthroughauth/auth.py
jupyterhub_passthroughauth-0.0.1.dist-info/LICENSE
jupyterhub_passthroughauth-0.0.1.dist-info/METADATA
jupyterhub_passthroughauth-0.0.1.dist-info/WHEEL
jupyterhub_passthroughauth-0.0.1.dist-info/top_level.txt
jupyterhub_passthroughauth-0.0.1.dist-info/RECORD
