Metadata-Version: 2.1
Name: jupyterhub-passthroughauth
Version: 0.0.1
Summary: Pass-through authentication for jupyterhub, enabling direct access to the session of a particular locked down user.
Home-page: https://github.com/rohitggarg/jupyterhub-passthroughauth
Author: Rohit Garg
Author-email: rohitgarg19@gmail.com
License: UNKNOWN
Project-URL: Bug Reports, https://github.com/rohitggarg/jupyterhub-passthroughauth/issues
Project-URL: Funding, https://www.paypal.me/rohitggarg
Project-URL: Say Thanks!, https://github.com/rohitggarg
Project-URL: Source, https://github.com/rohitggarg/jupyterhub-passthroughauth
Keywords: jupyter jupyterhub login autologin pass through guest access
Platform: UNKNOWN
Classifier: Development Status :: 3 - Alpha
Classifier: Intended Audience :: Developers
Classifier: Topic :: Software Development :: Libraries :: Python Modules
Classifier: License :: OSI Approved :: MIT License
Classifier: Programming Language :: Python :: 2
Classifier: Programming Language :: Python :: 2.7
Classifier: Programming Language :: Python :: 3
Classifier: Programming Language :: Python :: 3.4
Classifier: Programming Language :: Python :: 3.5
Classifier: Programming Language :: Python :: 3.6
Classifier: Programming Language :: Python :: 3.7
Requires-Python: >=2.7, <4
Requires-Dist: jupyterhub
Provides-Extra: dev
Requires-Dist: check-manifest ; extra == 'dev'
Provides-Extra: test
Requires-Dist: coverage ; extra == 'test'
